PyGaussian/__init__.py
PyGaussian/kernel.py
PyGaussian/model.py
PyGaussian-0.0.2.dist-info/LICENSE
PyGaussian-0.0.2.dist-info/METADATA
PyGaussian-0.0.2.dist-info/WHEEL
PyGaussian-0.0.2.dist-info/top_level.txt
PyGaussian-0.0.2.dist-info/RECORD
