Metadata-Version: 2.1
Name: PyGaussian
Version: 0.0.2
Home-page: https://github.com/nobodyPerfecZ/py-gaussian
Author: ['Dennis J.']
Requires-Python: >=3.10
License-File: LICENSE
Requires-Dist: numpy
Requires-Dist: scipy
